airML/__init__.py
airML/airML.py
airML/kbox-v0.0.2-beta.jar
airML-0.0.3.dist-info/LICENCE.txt
airML-0.0.3.dist-info/LICENSE
airML-0.0.3.dist-info/METADATA
airML-0.0.3.dist-info/WHEEL
airML-0.0.3.dist-info/entry_points.txt
airML-0.0.3.dist-info/top_level.txt
airML-0.0.3.dist-info/RECORD
