Metadata-Version: 2.1
Name: airML
Version: 0.0.3
Summary: application will allow users to share and dereference ML models.
Home-page: https://github.com/AKSW/airML
Author: Lahiru Oshara Hinguruduwa
Author-email: oshara.16@cse.mrt.ac.lk
License: Apache
Platform: UNKNOWN
Classifier: License :: OSI Approved :: Apache Software License
Classifier: Programming Language :: Python :: 3
Requires-Dist: click (>=7.1.2)
